MANIFEST.in
ez_setup.py
setup.py
CmtStandardNames.egg-info/PKG-INFO
CmtStandardNames.egg-info/SOURCES.txt
CmtStandardNames.egg-info/dependency_links.txt
CmtStandardNames.egg-info/entry_points.txt
CmtStandardNames.egg-info/pbr.json
CmtStandardNames.egg-info/requires.txt
CmtStandardNames.egg-info/top_level.txt
standard_names/__init__.py
standard_names/collection.py
standard_names/decorators.py
standard_names/io.py
standard_names/standardname.py
standard_names/validnames.py
standard_names/cmd/__init__.py
standard_names/cmd/snbuild.py
standard_names/cmd/sndump.py
standard_names/cmd/snscrape.py
standard_names/cmd/snsql.py
standard_names/data/standard_names.yaml
standard_names/tests/__init__.py
standard_names/tests/test_collection.py
standard_names/tests/test_io.py
standard_names/tests/test_standardname.py