Metadata-Version: 1.0
Name: CmtStandardNames
Version: 0.2.2
Summary: CSDMS standard names
Home-page: https://csdms.colorado.edu
Author: Eric Hutton
Author-email: eric.hutton@colorado.edu
License: UNKNOWN
Platform: UNKNOWN
